{"status":{"code":0,"message":"OK"},"data":{"paints":[{"id":"64b650769313055ba532ae43","type":"PAINT","thumbnail":null,"resource":"https:\/\/jigsaw-cdn.dailyinnovation.biz\/a29a572aa3e46f2d4c145ebb38b33531.jpeg","categories":["COL"],"module":"LIBRARY","mode":"NORMAL","daily":null,"unlock_type":"FREE","unlock_cost":0,"schedule_type":"OP","major_content_tags":["针织毛线"]},{"id":"63eb60a11be6ac9ae0a1a393","type":"PAINT","thumbnail":"","resource":"https:\/\/jigsaw-cdn.dailyinnovation.biz\/d1fbfa799a1623dcb8282d162c89791f.jpg","categories":["charming_houses"],"module":"LIBRARY","mode":"NORMAL","daily":null,"unlock_type":"FREE","unlock_cost":0,"schedule_type":"OP","major_content_tags":["独栋房屋"]},{"id":"64aea0079313055ba53215ec","type":"PAINT","thumbnail":"","resource":"https:\/\/jigsaw-cdn.dailyinnovation.biz\/ac3e88ba8a2190132e7b59cb158f0527.jpg","categories":["PET"],"module":"LIBRARY","mode":"NORMAL","daily":null,"unlock_type":"FREE","unlock_cost":0,"schedule_type":"OP","major_content_tags":["宠物猫"]},{"id":"6454d2b33aa9895f1b246c26","type":"PAINT","thumbnail":"","resource":"https:\/\/jigsaw-cdn.dailyinnovation.biz\/85ea321f8175dae43eee586a08d01597.jpeg","categories":["PET","DRA"],"module":"LIBRARY","mode":"NORMAL","daily":null,"unlock_type":"FREE","unlock_cost":0,"schedule_type":"OP","major_content_tags":["宠物狗"]},{"id":"649da050d5f8ce50f9806e6f","type":"PAINT","thumbnail":"","resource":"https:\/\/jigsaw-cdn.dailyinnovation.biz\/f3aacf9ff8f3ee03da78ceba0c0a237a.jpeg","categories":["FOO"],"module":"LIBRARY","mode":"NORMAL","daily":null,"unlock_type":"FREE","unlock_cost":0,"schedule_type":"OP","major_content_tags":["甜甜圈"]},{"id":"642e95746a19448e1f86bb26","type":"PAINT","thumbnail":null,"resource":"https:\/\/jigsaw-cdn.dailyinnovation.biz\/0553ab06e849bf30c96af349fbdaf30a.jpeg","categories":[],"module":"LIBRARY","mode":"MYSTERY","daily":null,"unlock_type":"FREE","unlock_cost":0,"schedule_type":"OP","major_content_tags":["多栋房屋"]},{"id":"64ae9f549313055ba53215cd","type":"PAINT","thumbnail":"https:\/\/jigsaw-cdn.dailyinnovation.biz\/37e67b9f98012f3299cea48864bf3a44.jpg","resource":"https:\/\/jigsaw-cdn.dailyinnovation.biz\/8418952f7ac080a99a672a63d1a16416.jpg","categories":["countryside"],"module":"LIBRARY","mode":"NORMAL","daily":null,"unlock_type":"FREE","unlock_cost":0,"schedule_type":"OP","major_content_tags":["独栋房屋"]},{"id":"6492ddcd1ae5fb72cadbfc19","type":"PAINT","thumbnail":"","resource":"https:\/\/jigsaw-cdn.dailyinnovation.biz\/0f54d630ed6f07bdbb9d53984354c9a0.jpg","categories":["NAT"],"module":"LIBRARY","mode":"NORMAL","daily":null,"unlock_type":"FREE","unlock_cost":0,"schedule_type":"OP","major_content_tags":["礁石"]},{"id":"649acc73d5f8ce50f9804b02","type":"PAINT","thumbnail":"","resource":"https:\/\/jigsaw-cdn.dailyinnovation.biz\/dcef00fc71bf3a579ab474e1f3f5087f.jpg","categories":["FLO"],"module":"LIBRARY","mode":"NORMAL","daily":null,"unlock_type":"FREE","unlock_cost":0,"schedule_type":"OP","major_content_tags":["花束"]},{"id":"64981db71ae5fb72cadc10ed","type":"PAINT","thumbnail":"","resource":"https:\/\/jigsaw-cdn.dailyinnovation.biz\/a2871a382b3d0670cb5311c432263d00.jpeg","categories":["NAT"],"module":"LIBRARY","mode":"NORMAL","daily":null,"unlock_type":"FREE","unlock_cost":0,"schedule_type":"OP","major_content_tags":["树"]},{"id":"647481cc2102ac5b93e15c33","type":"PAINT","thumbnail":"","resource":"https:\/\/jigsaw-cdn.dailyinnovation.biz\/b11bf91979c62640bf2afa41a12a8f97.jpeg","categories":["DRA"],"module":"LIBRARY","mode":"NORMAL","daily":null,"unlock_type":"FREE","unlock_cost":0,"schedule_type":"OP","major_content_tags":["兔子"]},{"id":"649da060d5f8ce50f9806e86","type":"PAINT","thumbnail":"","resource":"https:\/\/jigsaw-cdn.dailyinnovation.biz\/f36116fb6e82ade63b72a60cc82cd065.jpeg","categories":["FLO"],"module":"LIBRARY","mode":"NORMAL","daily":null,"unlock_type":"FREE","unlock_cost":0,"schedule_type":"OP","major_content_tags":["心形花"]},{"id":"6475e76c2102ac5b93e1a5d3","type":"PAINT","thumbnail":null,"resource":"https:\/\/jigsaw-cdn.dailyinnovation.biz\/43aafcf6172bdfdd2731a556f25306de.jpeg","categories":["OBJ"],"module":"LIBRARY","mode":"NORMAL","daily":null,"unlock_type":"FREE","unlock_cost":0,"schedule_type":"OP","major_content_tags":["鸟窝"]},{"id":"63e0d75a15945b3985995ac8","type":"PAINT","thumbnail":"","resource":"https:\/\/jigsaw-cdn.dailyinnovation.biz\/9c22051783fb190a2cc4b1cb7744c351.jpeg","categories":["COL"],"module":"LIBRARY","mode":"NORMAL","daily":null,"unlock_type":"FREE","unlock_cost":0,"schedule_type":"OP","major_content_tags":["平铺图案"]},{"id":"6463575ff2485c91428d43f7","type":"PAINT","thumbnail":null,"resource":"https:\/\/jigsaw-cdn.dailyinnovation.biz\/4b9aa7db0ca0200b0bee5646b9556fff.jpg","categories":["PET"],"module":"LIBRARY","mode":"NORMAL","daily":null,"unlock_type":"FREE","unlock_cost":0,"schedule_type":"OP","major_content_tags":["宠物狗"]},{"id":"6479c3159fee2ae4d98f1aab","type":"PAINT","thumbnail":null,"resource":"https:\/\/jigsaw-cdn.dailyinnovation.biz\/c80054afe9b9a29cc074a903bd64a659.jpg","categories":["charming_houses"],"module":"LIBRARY","mode":"NORMAL","daily":null,"unlock_type":"FREE","unlock_cost":0,"schedule_type":"OP","major_content_tags":["独栋房屋"]},{"id":"64562e413aa9895f1b248198","type":"PAINT","thumbnail":"","resource":"https:\/\/jigsaw-cdn.dailyinnovation.biz\/239fb91baa61d53ee7f65a6b35a1d338.jpg","categories":["FOO","COL"],"module":"LIBRARY","mode":"NORMAL","daily":null,"unlock_type":"FREE","unlock_cost":0,"schedule_type":"OP","major_content_tags":["奶茶果汁"]},{"id":"6492ddcf1ae5fb72cadbfc1c","type":"PAINT","thumbnail":"","resource":"https:\/\/jigsaw-cdn.dailyinnovation.biz\/0c5f02d2509051d3fdbf80440f759f1b.jpg","categories":["NAT"],"module":"LIBRARY","mode":"NORMAL","daily":null,"unlock_type":"FREE","unlock_cost":0,"schedule_type":"OP","major_content_tags":["湖"]},{"id":"642aa1122709bfc144c31e22","type":"PAINT","thumbnail":"","resource":"https:\/\/jigsaw-cdn.dailyinnovation.biz\/e094248ac36704a27ebef93c262f3144.jpg","categories":["NAT"],"module":"LIBRARY","mode":"NORMAL","daily":null,"unlock_type":"FREE","unlock_cost":0,"schedule_type":"OP","major_content_tags":["连绵山脉"]},{"id":"622b133bd04cbab22ad69b14","type":"PAINT","thumbnail":null,"resource":"https:\/\/jigsaw-cdn.dailyinnovation.biz\/AdobeStock_160683747.jpeg","categories":["HOM","SEA"],"module":"LIBRARY","mode":"NORMAL","daily":null,"unlock_type":"FREE","unlock_cost":0,"schedule_type":"OP","major_content_tags":["阳台"]},{"id":"6487013eb2aadc44a3095a1a","type":"PAINT","thumbnail":"","resource":"https:\/\/jigsaw-cdn.dailyinnovation.biz\/5745dbad500318259542ca6f244d654e.jpeg","categories":["PET"],"module":"LIBRARY","mode":"NORMAL","daily":null,"unlock_type":"FREE","unlock_cost":0,"schedule_type":"OP","major_content_tags":["宠物猫"]},{"id":"63e2293f15945b3985996811","type":"PAINT","thumbnail":"","resource":"https:\/\/jigsaw-cdn.dailyinnovation.biz\/76f51e4f5e744b3ce9352b3151e4b30c.jpeg","categories":["charming_houses"],"module":"LIBRARY","mode":"NORMAL","daily":null,"unlock_type":"FREE","unlock_cost":0,"schedule_type":"OP","major_content_tags":["独栋房屋"]},{"id":"64635740f2485c91428d43ca","type":"PAINT","thumbnail":"","resource":"https:\/\/jigsaw-cdn.dailyinnovation.biz\/7d6a98e3de3e67b2c5226d4a9b3974b9.jpg","categories":["COL"],"module":"LIBRARY","mode":"NORMAL","daily":null,"unlock_type":"FREE","unlock_cost":0,"schedule_type":"OP","major_content_tags":["伞"]},{"id":"637f5cf18062ac7fcbcb0f87","type":"PAINT","thumbnail":"","resource":"https:\/\/jigsaw-cdn.dailyinnovation.biz\/8492c6611079e3d1bc52282f47ef9872.jpeg","categories":["BIR"],"module":"LIBRARY","mode":"NORMAL","daily":null,"unlock_type":"FREE","unlock_cost":0,"schedule_type":"OP","major_content_tags":["其他鸟"]},{"id":"64aea0029313055ba53215e5","type":"PAINT","thumbnail":null,"resource":"https:\/\/jigsaw-cdn.dailyinnovation.biz\/318b17fb61cb3d63169be8b7122cb4f1.jpg","categories":["NAT"],"module":"LIBRARY","mode":"NORMAL","daily":null,"unlock_type":"FREE","unlock_cost":0,"schedule_type":"OP","major_content_tags":["礁石"]},{"id":"641c3e722709bfc144c23bd6","type":"PAINT","thumbnail":"","resource":"https:\/\/jigsaw-cdn.dailyinnovation.biz\/3f1f7f15bf919f63b72981f49458c187.jpg","categories":["FOO"],"module":"LIBRARY","mode":"NORMAL","daily":null,"unlock_type":"FREE","unlock_cost":0,"schedule_type":"OP","major_content_tags":["蛋糕"]},{"id":"6478830c9fee2ae4d98f0f05","type":"PAINT","thumbnail":"","resource":"https:\/\/jigsaw-cdn.dailyinnovation.biz\/5cb341d40c602d02735a83e867f05255.jpeg","categories":["HOM"],"module":"LIBRARY","mode":"NORMAL","daily":null,"unlock_type":"FREE","unlock_cost":0,"schedule_type":"OP","major_content_tags":["沙发摇椅"]},{"id":"64ad19249313055ba531f1b7","type":"PAINT","thumbnail":"","resource":"https:\/\/jigsaw-cdn.dailyinnovation.biz\/e2eff75cd0ca8eb0af593b5885af6505.jpeg","categories":["islands"],"module":"LIBRARY","mode":"NORMAL","daily":null,"unlock_type":"FREE","unlock_cost":0,"schedule_type":"OP","major_content_tags":["岛屿"]},{"id":"64a413efd5f8ce50f9809efe","type":"PAINT","thumbnail":null,"resource":"https:\/\/jigsaw-cdn.dailyinnovation.biz\/fc72316e40199847b69935398a83c6ad.jpg","categories":["NAT"],"module":"LIBRARY","mode":"NORMAL","daily":null,"unlock_type":"FREE","unlock_cost":0,"schedule_type":"OP","major_content_tags":["湖"]},{"id":"648ae573b2aadc44a309805d","type":"PAINT","thumbnail":"","resource":"https:\/\/jigsaw-cdn.dailyinnovation.biz\/dc48cdb09d4f947bf601fba03ac782a1.jpg","categories":["NAT","bestofjuly"],"module":"LIBRARY","mode":"NORMAL","daily":null,"unlock_type":"FREE","unlock_cost":0,"schedule_type":"OP","major_content_tags":["花海"]},{"id":"649d2852d5f8ce50f9806548","desc":"Tent Moments","resource":"https:\/\/jigsaw-cdn.dailyinnovation.biz\/8a6e761a707929db5c2541a96a3c1350.jpg","type":"COLLECTION","unlock_type":"CURRENCY","unlock_cost":400,"paint_count":16},{"id":"64105edd2198b6f625440c77","type":"PAINT","thumbnail":"","resource":"https:\/\/jigsaw-cdn.dailyinnovation.biz\/3179e69e9c495297ed83abcba84c19bf.jpeg","categories":["countryside"],"module":"LIBRARY","mode":"NORMAL","daily":null,"unlock_type":"FREE","unlock_cost":0,"schedule_type":"OP","major_content_tags":["村庄"]},{"id":"64981dbd1ae5fb72cadc10f7","type":"PAINT","thumbnail":null,"resource":"https:\/\/jigsaw-cdn.dailyinnovation.biz\/f46a1a0a5e7e62311904bbdadc7ca6df.jpeg","categories":["NAT"],"module":"LIBRARY","mode":"NORMAL","daily":null,"unlock_type":"FREE","unlock_cost":0,"schedule_type":"OP","major_content_tags":["森林"]},{"id":"647732729fee2ae4d98f00f8","type":"PAINT","thumbnail":null,"resource":"https:\/\/jigsaw-cdn.dailyinnovation.biz\/12f1fd3bcd40dc1342730fb1c979d989.jpg","categories":["PET"],"module":"LIBRARY","mode":"NORMAL","daily":null,"unlock_type":"FREE","unlock_cost":0,"schedule_type":"OP","major_content_tags":["宠物狗"]},{"id":"647db5ae9fee2ae4d98f2a05","type":"PAINT","thumbnail":null,"resource":"https:\/\/jigsaw-cdn.dailyinnovation.biz\/de72e67db6e66809641ecae3bff91b16.jpeg","categories":["COL"],"module":"LIBRARY","mode":"NORMAL","daily":null,"unlock_type":"FREE","unlock_cost":0,"schedule_type":"OP","major_content_tags":["玫瑰"]},{"id":"64884d38b2aadc44a30967e4","type":"PAINT","thumbnail":"","resource":"https:\/\/jigsaw-cdn.dailyinnovation.biz\/7d6060717649b68aa7aca0799cf13824.jpg","categories":["islands"],"module":"LIBRARY","mode":"NORMAL","daily":null,"unlock_type":"FREE","unlock_cost":0,"schedule_type":"OP","major_content_tags":["独栋房屋"]},{"id":"643fc91be616ced1543c0946","type":"PAINT","thumbnail":"","resource":"https:\/\/jigsaw-cdn.dailyinnovation.biz\/f644f1b4e9450ef330c90785e2b01b17.jpeg","categories":["man_made_scenery"],"module":"LIBRARY","mode":"NORMAL","daily":null,"unlock_type":"FREE","unlock_cost":0,"schedule_type":"OP","major_content_tags":["灯塔"]},{"id":"6487013bb2aadc44a3095a17","type":"PAINT","thumbnail":null,"resource":"https:\/\/jigsaw-cdn.dailyinnovation.biz\/1d6759feb1a36b0a8ef16ef2c12b3d6b.jpeg","categories":["ANI","bestofjuly"],"module":"LIBRARY","mode":"NORMAL","daily":null,"unlock_type":"FREE","unlock_cost":0,"schedule_type":"OP","major_content_tags":["蝴蝶"]},{"id":"64a2ce3ed5f8ce50f9808db6","type":"PAINT","thumbnail":"","resource":"https:\/\/jigsaw-cdn.dailyinnovation.biz\/c4c947f32c8d88cd6bfa0b9bd2e77f7b.jpg","categories":["FOO"],"module":"LIBRARY","mode":"NORMAL","daily":null,"unlock_type":"FREE","unlock_cost":0,"schedule_type":"OP","major_content_tags":["马卡龙"]},{"id":"646756a6f28f95ddf6dd1f10","type":"PAINT","thumbnail":"","resource":"https:\/\/jigsaw-cdn.dailyinnovation.biz\/30e81a85dbac4a1d40936915f96a8d24.jpg","categories":["charming_houses"],"module":"LIBRARY","mode":"NORMAL","daily":null,"unlock_type":"FREE","unlock_cost":0,"schedule_type":"OP","major_content_tags":["独栋房屋"]},{"id":"646de88be72c4297fd3236a7","type":"PAINT","thumbnail":"","resource":"https:\/\/jigsaw-cdn.dailyinnovation.biz\/409aabed2772a0cf81b8bccdf58dee65.jpg","categories":["NAT"],"module":"LIBRARY","mode":"NORMAL","daily":null,"unlock_type":"FREE","unlock_cost":0,"schedule_type":"OP","major_content_tags":["瀑布"]},{"id":"6492de0f1ae5fb72cadbfc2f","type":"PAINT","thumbnail":"","resource":"https:\/\/jigsaw-cdn.dailyinnovation.biz\/d2d0e4a7cfb6aee6769e6ca12f8a81d0.jpg","categories":["BIR"],"module":"LIBRARY","mode":"NORMAL","daily":null,"unlock_type":"FREE","unlock_cost":0,"schedule_type":"OP","major_content_tags":["其他鸟"]},{"id":"637619c2231933abb2704eee","type":"PAINT","thumbnail":null,"resource":"https:\/\/jigsaw-cdn.dailyinnovation.biz\/9ac0d1fa339f08a65aa22fcc1d3fe440.jpg","categories":["DRA"],"module":"LIBRARY","mode":"NORMAL","daily":null,"unlock_type":"FREE","unlock_cost":0,"schedule_type":"OP","major_content_tags":["其他建筑"]},{"id":"64ad1eed9313055ba531f2f3","type":"PAINT","thumbnail":null,"resource":"https:\/\/jigsaw-cdn.dailyinnovation.biz\/222c6c158dba5c4c455b63d8aba94a7c.jpg","categories":["NAT","bestofjuly"],"module":"LIBRARY","mode":"NORMAL","daily":null,"unlock_type":"FREE","unlock_cost":0,"schedule_type":"OP","major_content_tags":["海洋"]},{"id":"64395442e616ced1543ba848","type":"PAINT","thumbnail":"","resource":"https:\/\/jigsaw-cdn.dailyinnovation.biz\/64698c0446552a1614f56ce44f03df39.jpeg","categories":["ANI"],"module":"LIBRARY","mode":"NORMAL","daily":null,"unlock_type":"FREE","unlock_cost":0,"schedule_type":"OP","major_content_tags":["马"]},{"id":"6481adfcf8a7aa79d46abf2a","type":"PAINT","thumbnail":"","resource":"https:\/\/jigsaw-cdn.dailyinnovation.biz\/c8684149900ccc10b8744389bdc51dce.jpeg","categories":["PET"],"module":"LIBRARY","mode":"NORMAL","daily":null,"unlock_type":"FREE","unlock_cost":0,"schedule_type":"OP","major_content_tags":["宠物猫"]},{"id":"6464ac9ab5272586cd4be018","type":"PAINT","thumbnail":"","resource":"https:\/\/jigsaw-cdn.dailyinnovation.biz\/e1074b8d7756c7c49d4b19a5f8b28374.jpg","categories":["charming_houses"],"module":"LIBRARY","mode":"NORMAL","daily":null,"unlock_type":"FREE","unlock_cost":0,"schedule_type":"OP","major_content_tags":["独栋房屋"]},{"id":"647db58b9fee2ae4d98f29d9","type":"PAINT","thumbnail":"","resource":"https:\/\/jigsaw-cdn.dailyinnovation.biz\/a2b718a1708a2007b5871851d19a3765.jpeg","categories":["FOO","COL"],"module":"LIBRARY","mode":"NORMAL","daily":null,"unlock_type":"FREE","unlock_cost":0,"schedule_type":"OP","major_content_tags":["水果组合"]},{"id":"646de887e72c4297fd3236a3","type":"PAINT","thumbnail":"","resource":"https:\/\/jigsaw-cdn.dailyinnovation.biz\/8dac108a2d51b24df7f7ee1edd10fc81.jpg","categories":["BIR"],"module":"LIBRARY","mode":"NORMAL","daily":null,"unlock_type":"FREE","unlock_cost":0,"schedule_type":"OP","major_content_tags":["其他鸟"]},{"id":"643d243ee616ced1543bc5c4","type":"PAINT","thumbnail":"","resource":"https:\/\/jigsaw-cdn.dailyinnovation.biz\/0a9d5cdff1affece263d14707195f49c.jpg","categories":["islands"],"module":"LIBRARY","mode":"NORMAL","daily":null,"unlock_type":"FREE","unlock_cost":0,"schedule_type":"OP","major_content_tags":["礁石"]},{"id":"646de8aae72c4297fd3236d4","type":"PAINT","thumbnail":"","resource":"https:\/\/jigsaw-cdn.dailyinnovation.biz\/193c9663b121bfbfcdff6a2c56560d5c.jpeg","categories":["COL"],"module":"LIBRARY","mode":"NORMAL","daily":null,"unlock_type":"FREE","unlock_cost":0,"schedule_type":"OP","major_content_tags":["抽象形状"]},{"id":"649e8b0ad5f8ce50f9807a02","type":"PAINT","thumbnail":null,"resource":"https:\/\/jigsaw-cdn.dailyinnovation.biz\/0b9a1b04c568a2c62485d047a2b375de.jpeg","categories":["FLO"],"module":"LIBRARY","mode":"NORMAL","daily":null,"unlock_type":"FREE","unlock_cost":0,"schedule_type":"OP","major_content_tags":["花瓶"]},{"id":"6441225fe616ced1543c19e8","type":"PAINT","thumbnail":null,"resource":"https:\/\/jigsaw-cdn.dailyinnovation.biz\/aaaa09afd7c8b77ac5460d625bc01175.jpeg","categories":["DRA"],"module":"LIBRARY","mode":"NORMAL","daily":null,"unlock_type":"FREE","unlock_cost":0,"schedule_type":"OP","major_content_tags":["雪山"]},{"id":"640859854ecce27a6fe062ef","type":"PAINT","thumbnail":null,"resource":"https:\/\/jigsaw-cdn.dailyinnovation.biz\/7542c19c86b45a2dc1bb3f5f1a58db8b.jpeg","categories":["NAT"],"module":"LIBRARY","mode":"NORMAL","daily":null,"unlock_type":"FREE","unlock_cost":0,"schedule_type":"OP","major_content_tags":["河"]},{"id":"645380983aa9895f1b24535b","type":"PAINT","thumbnail":"","resource":"https:\/\/jigsaw-cdn.dailyinnovation.biz\/54acbdb7b39714747028e0c9f0c2cc86.jpg","categories":["HOM"],"module":"LIBRARY","mode":"NORMAL","daily":null,"unlock_type":"VIDEO_OR_CURRENCY","unlock_cost":30,"schedule_type":"OP","major_content_tags":["客厅"]},{"id":"64ad417a9313055ba531f51a","type":"PAINT","thumbnail":null,"resource":"https:\/\/jigsaw-cdn.dailyinnovation.biz\/860e00063bd073e9c33fddd62a99e766.jpg","categories":["NAT","bestofjuly"],"module":"LIBRARY","mode":"NORMAL","daily":null,"unlock_type":"FREE","unlock_cost":0,"schedule_type":"OP","major_content_tags":["海洋"]},{"id":"64917e0cb2aadc44a309aa46","type":"PAINT","thumbnail":"","resource":"https:\/\/jigsaw-cdn.dailyinnovation.biz\/2d4342a5d3e10141ca0aa471ca84c612.jpeg","categories":["DRA","bestofjuly"],"module":"LIBRARY","mode":null,"daily":null,"unlock_type":"FREE","unlock_cost":0,"schedule_type":"OP","major_content_tags":["宠物狗"]},{"id":"647732699fee2ae4d98f00eb","type":"PAINT","thumbnail":null,"resource":"https:\/\/jigsaw-cdn.dailyinnovation.biz\/2d17828d3d826a0413a106ba752129f8.jpeg","categories":["charming_houses"],"module":"LIBRARY","mode":"NORMAL","daily":null,"unlock_type":"FREE","unlock_cost":0,"schedule_type":"OP","major_content_tags":["独栋房屋"]},{"id":"64996ab41ae5fb72cadc23dc","type":"PAINT","thumbnail":"","resource":"https:\/\/jigsaw-cdn.dailyinnovation.biz\/0d8fe4e73919065a325484a813306961.jpg","categories":["COL"],"module":"LIBRARY","mode":"NORMAL","daily":null,"unlock_type":"FREE","unlock_cost":0,"schedule_type":"OP","major_content_tags":["抽象形状"]},{"id":"6447a30a01e6c46b636d958f","type":"PAINT","thumbnail":null,"resource":"https:\/\/jigsaw-cdn.dailyinnovation.biz\/cd2b618f1a4d14753da3cfca0fc0daad.jpeg","categories":["BIR"],"module":"LIBRARY","mode":"NORMAL","daily":null,"unlock_type":"FREE","unlock_cost":0,"schedule_type":"OP","major_content_tags":["其他鸟"]},{"id":"64904856b2aadc44a3099e79","type":"PAINT","thumbnail":"","resource":"https:\/\/jigsaw-cdn.dailyinnovation.biz\/113ad6d59ffd79372c8617eeb24105a9.jpeg","categories":["man_made_scenery"],"module":"LIBRARY","mode":"NORMAL","daily":null,"unlock_type":"FREE","unlock_cost":0,"schedule_type":"OP","major_content_tags":["城市小镇"]},{"id":"649da058d5f8ce50f9806e7a","type":"PAINT","thumbnail":null,"resource":"https:\/\/jigsaw-cdn.dailyinnovation.biz\/70178f62fd4c336256ec3abbc627236e.jpg","categories":["NAT"],"module":"LIBRARY","mode":"NORMAL","daily":null,"unlock_type":"FREE","unlock_cost":0,"schedule_type":"OP","major_content_tags":["湖"]},{"id":"649e8b06d5f8ce50f98079fd","type":"PAINT","thumbnail":"","resource":"https:\/\/jigsaw-cdn.dailyinnovation.biz\/c9f4b25144015fd9813aeb1d0ac4adbe.jpeg","categories":["ANI"],"module":"LIBRARY","mode":"NORMAL","daily":null,"unlock_type":"FREE","unlock_cost":0,"schedule_type":"OP","major_content_tags":["熊猫"]},{"id":"63c7cfe115945b398598ec91","type":"PAINT","thumbnail":"","resource":"https:\/\/jigsaw-cdn.dailyinnovation.biz\/8a27bb4b881d3b4a1533bae3528a9659.jpg","categories":["FOO"],"module":"LIBRARY","mode":"NORMAL","daily":null,"unlock_type":"FREE","unlock_cost":0,"schedule_type":"OP","major_content_tags":["甜品组合"]},{"id":"6409de874ecce27a6fe0790d","type":"PAINT","thumbnail":null,"resource":"https:\/\/jigsaw-cdn.dailyinnovation.biz\/4db057eb8ccf2eb49998e03615517425.jpeg","categories":["NAT"],"module":"LIBRARY","mode":"NORMAL","daily":null,"unlock_type":"FREE","unlock_cost":0,"schedule_type":"OP","major_content_tags":["岛屿"]},{"id":"647db5b49fee2ae4d98f2a0d","type":"PAINT","thumbnail":"","resource":"https:\/\/jigsaw-cdn.dailyinnovation.biz\/d16336a967f6551df5321a4520deb202.jpg","categories":["PET"],"module":"LIBRARY","mode":"NORMAL","daily":null,"unlock_type":"FREE","unlock_cost":0,"schedule_type":"OP","major_content_tags":["宠物猫"]},{"id":"648c4188b2aadc44a3098f7b","type":"PAINT","thumbnail":null,"resource":"https:\/\/jigsaw-cdn.dailyinnovation.biz\/b56499ea945d58e7256b249e4b19bd93.jpg","categories":["islands"],"module":"LIBRARY","mode":"NORMAL","daily":null,"unlock_type":"FREE","unlock_cost":0,"schedule_type":"OP","major_content_tags":["多栋房屋"]},{"id":"64ae54c59313055ba5320daf","type":"PAINT","thumbnail":null,"resource":"https:\/\/jigsaw-cdn.dailyinnovation.biz\/839bd9e27bf91964eadaf56b180babc7.jpg","categories":["FOO"],"module":"LIBRARY","mode":"NORMAL","daily":null,"unlock_type":"FREE","unlock_cost":0,"schedule_type":"OP","major_content_tags":["糖果"]},{"id":"648c419db2aadc44a3098f97","type":"PAINT","thumbnail":"","resource":"https:\/\/jigsaw-cdn.dailyinnovation.biz\/c64c067183275e9de95226b8d4c63b1e.jpg","categories":["BIR"],"module":"LIBRARY","mode":"NORMAL","daily":null,"unlock_type":"FREE","unlock_cost":0,"schedule_type":"OP","major_content_tags":["鸳鸯"]},{"id":"6492ddd81ae5fb72cadbfc28","type":"PAINT","thumbnail":"","resource":"https:\/\/jigsaw-cdn.dailyinnovation.biz\/1f290c1fed1f9e8aa4be00610df84407.jpeg","categories":["DRA"],"module":"LIBRARY","mode":"NORMAL","daily":null,"unlock_type":"FREE","unlock_cost":0,"schedule_type":"OP","major_content_tags":["田野"]},{"id":"6408599f4ecce27a6fe06316","type":"PAINT","thumbnail":"","resource":"https:\/\/jigsaw-cdn.dailyinnovation.biz\/16401490a20d92a3906335d7240f7851.jpg","categories":["NAT"],"module":"LIBRARY","mode":"NORMAL","daily":null,"unlock_type":"FREE","unlock_cost":0,"schedule_type":"OP","major_content_tags":["树"]},{"id":"649047f6b2aadc44a3099e5d","type":"PAINT","thumbnail":"","resource":"https:\/\/jigsaw-cdn.dailyinnovation.biz\/9058c8ec993f6d41efb84129eb4b1c2e.jpg","categories":["HOM"],"module":"LIBRARY","mode":"NORMAL","daily":null,"unlock_type":"FREE","unlock_cost":0,"schedule_type":"OP","major_content_tags":["沙发摇椅"]},{"id":"6437ec39e616ced1543b8782","type":"PAINT","thumbnail":"","resource":"https:\/\/jigsaw-cdn.dailyinnovation.biz\/424162b806645d5ba7346dc4a3aa92e1.jpg","categories":["countryside"],"module":"LIBRARY","mode":"NORMAL","daily":null,"unlock_type":"FREE","unlock_cost":0,"schedule_type":"OP","major_content_tags":["村庄"]},{"id":"649acc63d5f8ce50f9804aeb","type":"PAINT","thumbnail":null,"resource":"https:\/\/jigsaw-cdn.dailyinnovation.biz\/31736fab0f54a2fc3612cd9b5995524a.jpeg","categories":["NAT"],"module":"LIBRARY","mode":"NORMAL","daily":null,"unlock_type":"FREE","unlock_cost":0,"schedule_type":"OP","major_content_tags":["湖"]},{"id":"644a6f483aa9895f1b242f04","type":"PAINT","thumbnail":"","resource":"https:\/\/jigsaw-cdn.dailyinnovation.biz\/c6db6e5c5293dc602aab359c8144b58a.jpg","categories":["ANI"],"module":"LIBRARY","mode":"NORMAL","daily":null,"unlock_type":"FREE","unlock_cost":0,"schedule_type":"OP","major_content_tags":["鹿"]},{"id":"647883199fee2ae4d98f0f17","type":"PAINT","thumbnail":"","resource":"https:\/\/jigsaw-cdn.dailyinnovation.biz\/19c55d3155c9d7e9b8fb198db8333694.jpeg","categories":["DRA","travel"],"module":"LIBRARY","mode":"NORMAL","daily":null,"unlock_type":"VIDEO_OR_CURRENCY","unlock_cost":30,"schedule_type":"OP","major_content_tags":["汽车"]},{"id":"645e1ab23aa9895f1b24f303","type":"PAINT","thumbnail":"","resource":"https:\/\/jigsaw-cdn.dailyinnovation.biz\/b0263ba241091aee296dcdb04f6dece8.jpg","categories":["islands","bestofjuly"],"module":"LIBRARY","mode":"NORMAL","daily":null,"unlock_type":"FREE","unlock_cost":0,"schedule_type":"OP","major_content_tags":["海洋"]},{"id":"64996aa41ae5fb72cadc23c4","type":"PAINT","thumbnail":"","resource":"https:\/\/jigsaw-cdn.dailyinnovation.biz\/55192310326da56a1475260a1ea8eb52.jpeg","categories":["PET"],"module":"LIBRARY","mode":"NORMAL","daily":null,"unlock_type":"FREE","unlock_cost":0,"schedule_type":"OP","major_content_tags":["宠物狗"]},{"id":"64a413dbd5f8ce50f9809ee4","type":"PAINT","thumbnail":null,"resource":"https:\/\/jigsaw-cdn.dailyinnovation.biz\/87895aa1645bd28bb0ac698d7ad80c97.jpeg","categories":["DRA","bestofjuly"],"module":"LIBRARY","mode":"NORMAL","daily":null,"unlock_type":"FREE","unlock_cost":0,"schedule_type":"OP","major_content_tags":["独栋房屋"]},{"id":"64996a941ae5fb72cadc23ad","type":"PAINT","thumbnail":null,"resource":"https:\/\/jigsaw-cdn.dailyinnovation.biz\/6c567c4c9556022713c1f3ea5c40c6ce.jpeg","categories":["COL"],"module":"LIBRARY","mode":"NORMAL","daily":null,"unlock_type":"FREE","unlock_cost":0,"schedule_type":"OP","major_content_tags":["抽象形状"]},{"id":"63f8bd0a097b43395ea24951","type":"PAINT","thumbnail":"","resource":"https:\/\/jigsaw-cdn.dailyinnovation.biz\/e884cb0ee9c266202231b1a17d82db43.jpg","categories":["BIR"],"module":"LIBRARY","mode":"NORMAL","daily":null,"unlock_type":"FREE","unlock_cost":0,"schedule_type":"OP","major_content_tags":["企鹅"]},{"id":"649da069d5f8ce50f9806e91","type":"PAINT","thumbnail":null,"resource":"https:\/\/jigsaw-cdn.dailyinnovation.biz\/d39c897b37d21033a3dc05354c7bae32.jpeg","categories":["charming_houses"],"module":"LIBRARY","mode":"NORMAL","daily":null,"unlock_type":"FREE","unlock_cost":0,"schedule_type":"OP","major_content_tags":["多栋房屋"]},{"id":"6374ba50231933abb2703e5e","type":"PAINT","thumbnail":"","resource":"https:\/\/jigsaw-cdn.dailyinnovation.biz\/37c3dddbcd7e4a436edaaa4a757e8b9b.jpg","categories":["ART"],"module":"LIBRARY","mode":"NORMAL","daily":null,"unlock_type":"FREE","unlock_cost":0,"schedule_type":"OP","major_content_tags":["松鼠"]},{"id":"632afab660de5ff993ed4e95","type":"PAINT","thumbnail":"","resource":"https:\/\/jigsaw-cdn.dailyinnovation.biz\/fb9e63b4886612cf1c0ff210f92def5b.jpeg","categories":["FOO"],"module":"LIBRARY","mode":"NORMAL","daily":null,"unlock_type":"FREE","unlock_cost":0,"schedule_type":"OP","major_content_tags":["蔬菜组合"]},{"id":"649047fab2aadc44a3099e62","type":"PAINT","thumbnail":null,"resource":"https:\/\/jigsaw-cdn.dailyinnovation.biz\/1db030477b4f5a8c1f415fc35386fd10.jpg","categories":["countryside"],"module":"LIBRARY","mode":"NORMAL","daily":null,"unlock_type":"FREE","unlock_cost":0,"schedule_type":"OP","major_content_tags":["风车"]},{"id":"640859884ecce27a6fe062f2","type":"PAINT","thumbnail":"","resource":"https:\/\/jigsaw-cdn.dailyinnovation.biz\/9a5660ec1a19f2bb990e5c88dcae04c6.jpeg","categories":["NAT"],"module":"LIBRARY","mode":"NORMAL","daily":null,"unlock_type":"FREE","unlock_cost":0,"schedule_type":"OP","major_content_tags":["瀑布"]},{"id":"6492ddd81ae5fb72cadbfc29","type":"PAINT","thumbnail":"","resource":"https:\/\/jigsaw-cdn.dailyinnovation.biz\/31406415714b9430b1a809fd950335fe.jpg","categories":["NAT"],"module":"LIBRARY","mode":"NORMAL","daily":null,"unlock_type":"FREE","unlock_cost":0,"schedule_type":"OP","major_content_tags":["霞光"]},{"id":"64996a9f1ae5fb72cadc23be","type":"PAINT","thumbnail":"","resource":"https:\/\/jigsaw-cdn.dailyinnovation.biz\/5022468282864b9b9b59becd134e5ca2.jpeg","categories":["PET"],"module":"LIBRARY","mode":"NORMAL","daily":null,"unlock_type":"FREE","unlock_cost":0,"schedule_type":"OP","major_content_tags":["宠物猫"]},{"id":"64807e179fee2ae4d98f4344","type":"PAINT","thumbnail":null,"resource":"https:\/\/jigsaw-cdn.dailyinnovation.biz\/16c7f3bd0782cf3bd48a7be79314663f.jpeg","categories":["FLO","man_made_scenery","bestofjuly"],"module":"LIBRARY","mode":"NORMAL","daily":null,"unlock_type":"FREE","unlock_cost":30,"schedule_type":"OP","major_content_tags":["鸟窝"]},{"id":"648ae561b2aadc44a309803b","type":"PAINT","thumbnail":"","resource":"https:\/\/jigsaw-cdn.dailyinnovation.biz\/dc96c69196f7163017f100fafe67b9e3.jpeg","categories":["COL"],"module":"LIBRARY","mode":"NORMAL","daily":null,"unlock_type":"FREE","unlock_cost":0,"schedule_type":"OP","major_content_tags":["彩虹"]},{"id":"64996c021ae5fb72cadc2449","type":"PAINT","thumbnail":"","resource":"https:\/\/jigsaw-cdn.dailyinnovation.biz\/1a845a09e83d9496487eaa95ca03b31d.jpeg","categories":["NAT"],"module":"LIBRARY","mode":"NORMAL","daily":null,"unlock_type":"FREE","unlock_cost":0,"schedule_type":"OP","major_content_tags":["湖"]},{"id":"6466148ff28f95ddf6dd067f","type":"PAINT","thumbnail":"","resource":"https:\/\/jigsaw-cdn.dailyinnovation.biz\/31ccc0fd364b681284c3ab6b0cbab3cc.jpg","categories":["BIR"],"module":"LIBRARY","mode":"NORMAL","daily":null,"unlock_type":"FREE","unlock_cost":0,"schedule_type":"OP","major_content_tags":["其他鸟"]},{"id":"64a41234d5f8ce50f9809ed6","type":"PAINT","thumbnail":"","resource":"https:\/\/jigsaw-cdn.dailyinnovation.biz\/da8d012848b53f9bf994d117a9224111.jpeg","categories":["FOO"],"module":"LIBRARY","mode":"NORMAL","daily":null,"unlock_type":"FREE","unlock_cost":0,"schedule_type":"OP","major_content_tags":["蛋糕"]},{"id":"646b56bff28f95ddf6dd3719","type":"PAINT","thumbnail":"","resource":"https:\/\/jigsaw-cdn.dailyinnovation.biz\/b9ecddcf17f271a6c06b9ea42eb4caf3.jpeg","categories":["charming_houses"],"module":"LIBRARY","mode":"NORMAL","daily":null,"unlock_type":"FREE","unlock_cost":0,"schedule_type":"OP","major_content_tags":["独栋房屋"]},{"id":"645380b23aa9895f1b24537f","type":"PAINT","thumbnail":"","resource":"https:\/\/jigsaw-cdn.dailyinnovation.biz\/fabbfb8c65392ec87c59ece1feb72a9b.jpeg","categories":["ANI"],"module":"LIBRARY","mode":"NORMAL","daily":null,"unlock_type":"FREE","unlock_cost":0,"schedule_type":"OP","major_content_tags":["热带鱼"]},{"id":"64884d57b2aadc44a309680e","type":"PAINT","thumbnail":"","resource":"https:\/\/jigsaw-cdn.dailyinnovation.biz\/e2a48fa809360bd123b5f0fd34145b8e.jpeg","categories":["FLO"],"module":"LIBRARY","mode":"NORMAL","daily":null,"unlock_type":"VIDEO_OR_CURRENCY","unlock_cost":30,"schedule_type":"OP","major_content_tags":["花束"]},{"id":"620c9af108a98e2f5a002538","type":"PAINT","thumbnail":"","resource":"https:\/\/jigsaw-cdn.dailyinnovation.biz\/AdobeStock_80632314.jpeg","categories":["ART"],"module":"LIBRARY","mode":"NORMAL","daily":null,"unlock_type":"FREE","unlock_cost":0,"schedule_type":"OP","major_content_tags":["陶器"]},{"id":"63c681892d7416019d9f3f01","type":"PAINT","thumbnail":"","resource":"https:\/\/jigsaw-cdn.dailyinnovation.biz\/14b878a59618cba7a662255980b706c6.jpeg","categories":["LAN"],"module":"LIBRARY","mode":"NORMAL","daily":null,"unlock_type":"FREE","unlock_cost":0,"schedule_type":"OP","major_content_tags":["埃菲尔铁塔"]},{"id":"6492ddd41ae5fb72cadbfc23","type":"PAINT","thumbnail":"","resource":"https:\/\/jigsaw-cdn.dailyinnovation.biz\/34690fa62504f397a01f6708b7f58829.jpg","categories":["NAT"],"module":"LIBRARY","mode":"NORMAL","daily":null,"unlock_type":"FREE","unlock_cost":0,"schedule_type":"OP","major_content_tags":["河"]},{"id":"64996a9d1ae5fb72cadc23ba","type":"PAINT","thumbnail":null,"resource":"https:\/\/jigsaw-cdn.dailyinnovation.biz\/e44c206dbb67b5cd07f063ea5ad79e3b.jpg","categories":["PET"],"module":"LIBRARY","mode":"NORMAL","daily":null,"unlock_type":"FREE","unlock_cost":0,"schedule_type":"OP","major_content_tags":["宠物狗"]},{"id":"64807e049fee2ae4d98f432c","type":"PAINT","thumbnail":null,"resource":"https:\/\/jigsaw-cdn.dailyinnovation.biz\/39301021574c7c634b580377791e4ed1.jpeg","categories":["COL","bestofjuly"],"module":"LIBRARY","mode":"NORMAL","daily":null,"unlock_type":"FREE","unlock_cost":0,"schedule_type":"OP","major_content_tags":["铅笔"]}],"total":10183}}